clover/__init__.py
clover/coverage2clover.py
coverage2clover-4.0.0.dist-info/LICENSE.txt
coverage2clover-4.0.0.dist-info/METADATA
coverage2clover-4.0.0.dist-info/WHEEL
coverage2clover-4.0.0.dist-info/entry_points.txt
coverage2clover-4.0.0.dist-info/top_level.txt
coverage2clover-4.0.0.dist-info/RECORD
