Metadata-Version: 2.1
Name: coverage2clover
Version: 4.0.0
Summary: A tool to convert python-coverage xml report to Atlassian Clover xml report format
Home-page: https://github.com/tumb1er/coverage2clover
Author: tumbler
Author-email: zimbler@gmail.com
License: Beer License
Classifier: Development Status :: 5 - Production/Stable
Classifier: Programming Language :: Python :: 3.7
Classifier: Programming Language :: Python :: 3.8
Classifier: Programming Language :: Python :: 3.9
Classifier: Programming Language :: Python :: 3.10
Classifier: Programming Language :: Python :: 3.11
Classifier: Topic :: Text Processing :: Markup :: XML
Classifier: Topic :: Software Development :: Quality Assurance
Classifier: Topic :: Software Development :: Testing
Requires-Python: >=3.6
License-File: LICENSE.txt
Requires-Dist: coverage (<8.0,>=5.3)
Requires-Dist: pygount (==1.2.4)
